HorridAPI/__init__.py
HorridAPI-3.40.dist-info/LICENSE
HorridAPI-3.40.dist-info/METADATA
HorridAPI-3.40.dist-info/WHEEL
HorridAPI-3.40.dist-info/top_level.txt
HorridAPI-3.40.dist-info/RECORD
