Metadata-Version: 2.1
Name: HorridAPI
Version: 3.40
Summary: Asynchronous Python Wrapper For HorridAPI
Home-page: https://github.com/Mishel-Tg/HorridAPI
Author: Horrid
Author-email: narutomalayalam@gmail.com
Keywords: API,HorridAPI,Mrz_bots,Horrid-API
Classifier: Programming Language :: Python :: 3
Classifier: Programming Language :: Python :: 3.7
Classifier: Programming Language :: Python :: 3.8
Classifier: Programming Language :: Python :: 3.9
Classifier: Programming Language :: Python :: 3.10
Classifier: Programming Language :: Python :: 3.11
Classifier: Development Status :: 5 - Production/Stable
Classifier: License :: OSI Approved :: MIT License
Classifier: Operating System :: OS Independent
Classifier: Intended Audience :: Developers
Classifier: Natural Language :: English
Requires-Python: ~=3.7
License-File: LICENSE
